{
  "video_id": "toutiao-7551391170828537122-fc49fff353e3",
  "frames": [
    {
      "path": "D:\\zhihu\\zhihu_file\\Videos\\keyframes\\toutiao-7551391170828537122\\frame_00001.jpg",
      "marker": "Frame [00:00:01] type=context diff=0"
    },
    {
      "path": "D:\\zhihu\\zhihu_file\\Videos\\keyframes\\toutiao-7551391170828537122\\frame_00002.jpg",
      "marker": "Frame [00:00:02] type=context diff=0"
    },
    {
      "path": "D:\\zhihu\\zhihu_file\\Videos\\keyframes\\toutiao-7551391170828537122\\frame_00023.jpg",
      "marker": "Frame [00:00:23] type=annotation diff=0.2868"
    }
  ],
  "events": [
    {
      "type": "annotation",
      "frame_idx": 22,
      "diff": 0.2868
    }
  ]
}
