{
  "schema_version": "short-video-pack-qc-v1",
  "pack_id": "pack-20260529-135509-009",
  "output_md": "D:\\zhihu\\zhihu_file\\runs\\short-video\\packs\\pack-20260529-135509-009.output.md",
  "expected_video_count": 8,
  "parsed_video_count": 8,
  "written_video_count": 8,
  "warnings": [],
  "videos": [
    {
      "video_id": "toutiao-7640703201901019657-ed26cc11e012",
      "source_status": "full",
      "body_status": "ok",
      "transcript_chars": 230,
      "body_chars": 1308,
      "body_transcript_ratio": 5.687,
      "timeline_status": "ok",
      "warnings": [],
      "markdown_path": "D:\\zhihu\\zhihu_file\\Markdowns\\TTS_short_toutiao-7640703201901019657-ed26cc11e012.md"
    },
    {
      "video_id": "toutiao-7640254275381183019-8bfd0837c877",
      "source_status": "full",
      "body_status": "ok",
      "transcript_chars": 230,
      "body_chars": 1424,
      "body_transcript_ratio": 6.1913,
      "timeline_status": "ok",
      "warnings": [],
      "markdown_path": "D:\\zhihu\\zhihu_file\\Markdowns\\TTS_short_toutiao-7640254275381183019-8bfd0837c877.md"
    },
    {
      "video_id": "toutiao-7639398415545156134-2ebe6518b4bd",
      "source_status": "full",
      "body_status": "ok",
      "transcript_chars": 207,
      "body_chars": 1278,
      "body_transcript_ratio": 6.1739,
      "timeline_status": "ok",
      "warnings": [],
      "markdown_path": "D:\\zhihu\\zhihu_file\\Markdowns\\TTS_short_toutiao-7639398415545156134-2ebe6518b4bd.md"
    },
    {
      "video_id": "toutiao-7482178312479965199-c02f0b8a1389",
      "source_status": "full",
      "body_status": "ok",
      "transcript_chars": 216,
      "body_chars": 1245,
      "body_transcript_ratio": 5.7639,
      "timeline_status": "ok",
      "warnings": [],
      "markdown_path": "D:\\zhihu\\zhihu_file\\Markdowns\\TTS_short_toutiao-7482178312479965199-c02f0b8a1389.md"
    },
    {
      "video_id": "toutiao-7632605950037197375-f52d3be3c1e5",
      "source_status": "full",
      "body_status": "ok",
      "transcript_chars": 215,
      "body_chars": 1379,
      "body_transcript_ratio": 6.414,
      "timeline_status": "ok",
      "warnings": [],
      "markdown_path": "D:\\zhihu\\zhihu_file\\Markdowns\\TTS_short_toutiao-7632605950037197375-f52d3be3c1e5.md"
    },
    {
      "video_id": "toutiao-7640457647321252386-2c8ce31db0af",
      "source_status": "full",
      "body_status": "ok",
      "transcript_chars": 166,
      "body_chars": 1295,
      "body_transcript_ratio": 7.8012,
      "timeline_status": "ok",
      "warnings": [],
      "markdown_path": "D:\\zhihu\\zhihu_file\\Markdowns\\TTS_short_toutiao-7640457647321252386-2c8ce31db0af.md"
    },
    {
      "video_id": "toutiao-7620380955924463643-2d59d25693be",
      "source_status": "full",
      "body_status": "ok",
      "transcript_chars": 1844,
      "body_chars": 3430,
      "body_transcript_ratio": 1.8601,
      "timeline_status": "ok",
      "warnings": [],
      "markdown_path": "D:\\zhihu\\zhihu_file\\Markdowns\\TTS_short_toutiao-7620380955924463643-2d59d25693be.md"
    },
    {
      "video_id": "toutiao-7562128956648882707-d11a51931fb8",
      "source_status": "full",
      "body_status": "ok",
      "transcript_chars": 241,
      "body_chars": 1368,
      "body_transcript_ratio": 5.6763,
      "timeline_status": "ok",
      "warnings": [],
      "markdown_path": "D:\\zhihu\\zhihu_file\\Markdowns\\TTS_short_toutiao-7562128956648882707-d11a51931fb8.md"
    }
  ]
}
